__init__.py
bellastore/database/db.py
bellastore/filesystem/fs.py
bellastore/scripts/backup.py
bellastore/scripts/main.py
bellastore/utils/constants.py
bellastore/utils/scan.py
bellastore-1.0.1.dist-info/licenses/LICENSE
bellastore-1.0.1.dist-info/METADATA
bellastore-1.0.1.dist-info/WHEEL
bellastore-1.0.1.dist-info/entry_points.txt
bellastore-1.0.1.dist-info/top_level.txt
bellastore-1.0.1.dist-info/RECORD
