Metadata-Version: 2.4
Name: bellastore
Version: 1.0.1
Summary: Digital pathology storage manager for WSI scans
Author: Paul Huettl and Lukas Wolfseher
Maintainer-email: Paul Huettl <paulhuettl@web.de>, Lukas Wolfseher <lukas.wolfseher@informatik.uni-regensburg.de>
Project-URL: Source, https://github.com/spang-lab/bellastore
Classifier: Programming Language :: Python :: 3
Classifier: License :: OSI Approved :: MIT License
Classifier: Operating System :: OS Independent
Requires-Python: >=3.10
License-File: LICENSE
Requires-Dist: pandas>=2.0.0
Dynamic: license-file
